{
    "__length_unit__": "mm",
    "__angle_unit__": "degree",
    "__force_unit__": "Newton",
    
    "pGeo": {
        "sections": [
            {
                "xLE": 0.0,
                "yLE": 0.0,
                "zLE": 0.0,
                "chord": 1000.0,
                "twist": 0.0,
                "airfoil": "BAC-NLF.dat",
                "t_cover": 4.0,
                "spars": [
                    {"x": 0.2, "t": 8.0},
                    {"x": 0.7, "t": 8.0}
                ],
                "stringers": [
                    {"x": 0.25, "t": 2.0, "h": 0.005, "w": 0.005},
                    {"x": 0.30, "t": 2.0, "h": 0.005, "w": 0.005},
                    {"x": 0.35, "t": 2.0, "h": 0.005, "w": 0.005},
                    {"x": 0.40, "t": 2.0, "h": 0.005, "w": 0.005},
                    {"x": 0.45, "t": 2.0, "h": 0.005, "w": 0.005},
                    {"x": 0.50, "t": 2.0, "h": 0.005, "w": 0.005},
                    {"x": 0.55, "t": 2.0, "h": 0.005, "w": 0.005},
                    {"x": 0.60, "t": 2.0, "h": 0.005, "w": 0.005},
                    {"x": 0.65, "t": 2.0, "h": 0.005, "w": 0.005}
                ],
                "cutouts": [
                    {"x": 0.45, "y": 0.005, "lx": 0.3, "ly": 0.05, "r_fillet": 0.01}
                ]
            },
            {
                "xLE": 200.0,
                "yLE": 50.0,
                "zLE": 500.0,
                "chord": 800.0,
                "twist": 2.0,
                "airfoil": "BAC-NLF.dat",
                "t_cover": 4.0,
                "spars": [
                    {"x": 0.2, "t": 8.0},
                    {"x": 0.7, "t": 8.0}
                ],
                "stringers": [
                    {"x": 0.25, "t": 2.0, "h": 0.005, "w": 0.005},
                    {"x": 0.30, "t": 2.0, "h": 0.005, "w": 0.005},
                    {"x": 0.35, "t": 2.0, "h": 0.005, "w": 0.005},
                    {"x": 0.40, "t": 2.0, "h": 0.005, "w": 0.005},
                    {"x": 0.45, "t": 2.0, "h": 0.005, "w": 0.005},
                    {"x": 0.50, "t": 2.0, "h": 0.005, "w": 0.005},
                    {"x": 0.55, "t": 2.0, "h": 0.005, "w": 0.005},
                    {"x": 0.60, "t": 2.0, "h": 0.005, "w": 0.005},
                    {"x": 0.65, "t": 2.0, "h": 0.005, "w": 0.005}
                ],
                "cutouts": [
                    {"x": 0.45, "y": 0.005, "lx": 0.3, "ly": 0.05, "r_fillet": 0.01}
                ]
            },
            {
                "xLE": 400.0,
                "yLE": 100.0,
                "zLE": 1000.0,
                "chord": 600.0,
                "twist": 4.0,
                "airfoil": "BAC-NLF.dat",
                "t_cover": 4.0,
                "spars": [
                    {"x": 0.2, "t": 8.0},
                    {"x": 0.7, "t": 8.0}
                ],
                "stringers": [
                    {"x": 0.25, "t": 2.0, "h": 0.005, "w": 0.005},
                    {"x": 0.30, "t": 2.0, "h": 0.005, "w": 0.005},
                    {"x": 0.35, "t": 2.0, "h": 0.005, "w": 0.005},
                    {"x": 0.40, "t": 2.0, "h": 0.005, "w": 0.005},
                    {"x": 0.45, "t": 2.0, "h": 0.005, "w": 0.005},
                    {"x": 0.50, "t": 2.0, "h": 0.005, "w": 0.005},
                    {"x": 0.55, "t": 2.0, "h": 0.005, "w": 0.005},
                    {"x": 0.60, "t": 2.0, "h": 0.005, "w": 0.005},
                    {"x": 0.65, "t": 2.0, "h": 0.005, "w": 0.005}
                ],
                "cutouts": [
                    {"x": 0.45, "y": 0.005, "lx": 0.3, "ly": 0.05, "r_fillet": 0.01}
                ]
            }
        ]
    },

    "pMesh": {

    },

    "pRun": {
        "timePeriod": 1.0,
        "maxNumInc": 10000000,
        "initialInc": 0.01,
        "minInc": 1e-15,
        "maxInc": 0.1,
        "nlgeom": false,
        "memory_max_percentage": 90,
        "numCpus": 4,
        "numThreadsPerMpiProcess": 1
    },

    "not_run_job": true

}
